flighted/__init__.py
flighted/common_utils.py
flighted/pretrained.py
flighted/featurization/__init__.py
flighted/featurization/embeddings.py
flighted/flighted_inference/__init__.py
flighted/flighted_inference/flighted_datasets.py
flighted/flighted_inference/flighted_models.py
flighted/flighted_inference/flighted_trainers.py
flighted/landscape_inference/__init__.py
flighted/landscape_inference/landscape_datasets.py
flighted/landscape_inference/landscape_models.py
flighted/landscape_inference/landscape_trainers.py
flighted-0.1.2.dist-info/LICENSE
flighted-0.1.2.dist-info/METADATA
flighted-0.1.2.dist-info/WHEEL
flighted-0.1.2.dist-info/top_level.txt
flighted-0.1.2.dist-info/RECORD
