Metadata-Version: 2.1
Name: flighted
Version: 0.1.2
Summary: FLIGHTED, a machine learning method for inference of fitness landscapes from high-throughput experimental data.
Author: Vikram Sundar
Author-email: vsundar@mit.edu
Project-URL: Homepage, https://github.com/vikram-sundar/FLIGHTED_public
Classifier: Programming Language :: Python :: 3
Classifier: License :: OSI Approved :: MIT License
Classifier: Operating System :: OS Independent
License-File: LICENSE
Requires-Dist: numpy
Requires-Dist: scipy
Requires-Dist: pandas
Requires-Dist: scikit-learn
Requires-Dist: matplotlib
Requires-Dist: seaborn
Requires-Dist: biopython
Requires-Dist: pytest
Requires-Dist: pytest-pylint
Requires-Dist: torch
Requires-Dist: black
Requires-Dist: isort
Requires-Dist: pre-commit
Requires-Dist: pyro-ppl
